setup.py
Flask_PAM.egg-info/PKG-INFO
Flask_PAM.egg-info/SOURCES.txt
Flask_PAM.egg-info/dependency_links.txt
Flask_PAM.egg-info/requires.txt
Flask_PAM.egg-info/top_level.txt
flask_pam/__init__.py
flask_pam/auth.py
flask_pam/token/__init__.py
flask_pam/token/jwt.py
flask_pam/token/simple.py
flask_pam/token/token.py
flask_pam/token_storage/__init__.py
flask_pam/token_storage/dict_storage.py
flask_pam/token_storage/token_storage.py