Metadata-Version: 1.0
Name: Flask-PAM
Version: 0.1rc1
Summary: Flask authentication using PAM
Home-page: https://github.com/KujiraProject/Flask-PAM
Author: Kacper Kołodziej
Author-email: kacper@kolodziej.in
License: UNKNOWN
Platform: UNKNOWN
